beoremote/__init__.py
beoremote/configuration.py
beoremote/halo.py
beoremote/cli/__init__.py
beoremote/cli/backend.py
beoremote/cli/cli.py
beoremote/cli/config_example.py
beoremote/cli/discover.py
beoremote/events/__init__.py
beoremote/events/buttonEvent.py
beoremote/events/entity.py
beoremote/events/event.py
beoremote/events/icons.py
beoremote/events/powerEvent.py
beoremote/events/statusEvent.py
beoremote/events/systemEvent.py
beoremote/events/text.py
beoremote/events/update.py
beoremote/events/updateButton.py
beoremote/events/updateDisplayPage.py
beoremote/events/updateNotification.py
beoremote/events/wheelEvent.py
beoremote_halo-1.0.2.dist-info/LICENSE
beoremote_halo-1.0.2.dist-info/METADATA
beoremote_halo-1.0.2.dist-info/WHEEL
beoremote_halo-1.0.2.dist-info/entry_points.txt
beoremote_halo-1.0.2.dist-info/top_level.txt
beoremote_halo-1.0.2.dist-info/RECORD
