Metadata-Version: 2.1
Name: beoremote-halo
Version: 1.0.2
Summary: Beoremote Halo connecting and configuring Home Automation Systems.
Home-page: https://github.com/bang-olufsen/beoremote-halo
Author: Bang & Olufsen
Author-email: support@bang-olufsen.dk
License: UNKNOWN
Project-URL: Bug Tracker, https://github.com/bang-olufsen/beoremote-halo/issues
Platform: UNKNOWN
Classifier: Programming Language :: Python :: 3
Classifier: License :: OSI Approved :: MIT License
Classifier: Operating System :: OS Independent
License-File: LICENSE
Requires-Dist: websocket-client
Requires-Dist: zeroconf
Requires-Dist: click
Requires-Dist: rel
